namdtools/__init__.py
namdtools/exceptions.py
namdtools/options.py
namdtools/core/__init__.py
namdtools/core/core.py
namdtools-0.0.23.dist-info/METADATA
namdtools-0.0.23.dist-info/WHEEL
namdtools-0.0.23.dist-info/top_level.txt
namdtools-0.0.23.dist-info/zip-safe
namdtools-0.0.23.dist-info/RECORD
